django_gapc_storage-0.5.1.dist-info/METADATA
django_gapc_storage-0.5.1.dist-info/RECORD
django_gapc_storage-0.5.1.dist-info/WHEEL
django_gapc_storage-0.5.1.dist-info/top_level.txt
gapc_storage/__init__.py
gapc_storage/storage.py
