Metadata-Version: 2.1
Name: django-gapc-storage
Version: 0.5.1
Summary: a Django storage backend using GCS JSON API
Home-page: http://github.com/eldarion/django-gapc-storage
Author: Eldarion, Inc.
Author-email: development@eldarion.com
License: BSD
Platform: UNKNOWN
Classifier: Development Status :: 3 - Alpha
Classifier: Environment :: Web Environment
Classifier: Intended Audience :: Developers
Classifier: License :: OSI Approved :: BSD License
Classifier: Operating System :: OS Independent
Classifier: Programming Language :: Python
Classifier: Framework :: Django
Requires-Dist: google-api-python-client (<=1.7,>=1.5.0)
Requires-Dist: oauth2client
Requires-Dist: python-dateutil
